evallite/__init__.py
evallite/model.py
evallite-0.2.0.dist-info/LICENSE
evallite-0.2.0.dist-info/METADATA
evallite-0.2.0.dist-info/WHEEL
evallite-0.2.0.dist-info/top_level.txt
evallite-0.2.0.dist-info/RECORD
